{
    "items": [
        {
            "id": "id1", 
            "vendor": "Power Company", 
            "vendorId": "power-company",
            "icon": "/assets/images/power-company.png",
            "period": "Dec 2017",
            "periodId": "12-2017",
            "amount": "23.49"
        },
        {
            "id": "id2", 
            "vendor": "Gas company", 
            "vendorId": "gas-company",
            "icon": "/assets/images/gas-company.png",
            "period": "Dec 2017",
            "periodId": "12-2017",
            "amount": "13.09"
        },
        {
            "id": "id3", 
            "vendor": "Water Company", 
            "vendorId": "water-company",
            "icon": "/assets/images/water-company.png",
            "period": "Dec 2017",
            "periodId": "12-2017",
            "amount": "20.59"
        },
        {
            "id": "id4", 
            "vendor": "Internet Provider",
            "vendorId": "internet-provider",
            "icon": "/assets/images/internet-provider.png",
            "period": "Dec 2017",
            "periodId": "12-2017",
            "amount": "51.99"
        }
    ]
}